metator/__init__.py
metator/align.py
metator/commands.py
metator/contact_map.py
metator/figures.py
metator/host.py
metator/io.py
metator/log.py
metator/main.py
metator/mge.py
metator/network.py
metator/partition.py
metator/quality_check.py
metator/regions.py
metator/scaffold.py
metator/validation.py
metator/version.py
metator/bin/convert
metator/bin/hierarchy
metator/bin/louvain
metator/bin/matrix
metator/bin/networkanalysis-1.3.0.jar
metator-1.3.10.dist-info/METADATA
metator-1.3.10.dist-info/WHEEL
metator-1.3.10.dist-info/entry_points.txt
metator-1.3.10.dist-info/licenses/LICENSE
metator-1.3.10.dist-info/RECORD
