Metadata-Version: 2.4
Name: metator
Version: 1.3.10
Summary: A pipeline for binning metagenomic datasets from metaHiC data.
Project-URL: homepage, https://github.com/koszullab/metator
Project-URL: documentation, https://github.com/koszullab/metator
Project-URL: repository, https://github.com/koszullab/metator
Project-URL: changelog, https://github.com/koszullab/metator/blob/devel/CHANGELOG.md
Author-email: Amaury Bignaud <amaury.bignaud@pasteur.fr>, Jacques Serizay <jacques.serizay@pasteur.fr>
License: GNU General Public License v3 (GPLv3)
License-File: LICENSE
Keywords: bioinformatics,metagenomics
Classifier: Development Status :: 3 - Alpha
Classifier: Intended Audience :: Science/Research
Classifier: License :: OSI Approved :: GNU General Public License v3 (GPLv3)
Classifier: Operating System :: Unix
Classifier: Programming Language :: Python
Classifier: Programming Language :: Python :: 3
Classifier: Programming Language :: Python :: 3 :: Only
Classifier: Topic :: Scientific/Engineering
Classifier: Topic :: Scientific/Engineering :: Bio-Informatics
Classifier: Topic :: Scientific/Engineering :: Visualization
Requires-Python: <3.13,>=3.9
Requires-Dist: biopython<=1.80
Requires-Dist: checkv
Requires-Dist: cooler
Requires-Dist: hicstuff
Requires-Dist: looseversion
Requires-Dist: micomplete
Requires-Dist: networkx
Requires-Dist: numpy
Requires-Dist: pairtools
Requires-Dist: pandas
Requires-Dist: pyfastx
Requires-Dist: pypairix
Requires-Dist: pysam
Requires-Dist: scikit-learn
Requires-Dist: scipy
Requires-Dist: seaborn
Provides-Extra: dev
Requires-Dist: autodoc; extra == 'dev'
Requires-Dist: autodocsumm; extra == 'dev'
Requires-Dist: black; extra == 'dev'
Requires-Dist: codecov; extra == 'dev'
Requires-Dist: coverage[toml]; extra == 'dev'
Requires-Dist: furo; extra == 'dev'
Requires-Dist: hatch; extra == 'dev'
Requires-Dist: hatch-build-scripts; extra == 'dev'
Requires-Dist: hatchling; extra == 'dev'
Requires-Dist: ipython; extra == 'dev'
Requires-Dist: isort; extra == 'dev'
Requires-Dist: lxml[html-clean]; extra == 'dev'
Requires-Dist: m2r; extra == 'dev'
Requires-Dist: mypy; extra == 'dev'
Requires-Dist: myst-parser; extra == 'dev'
Requires-Dist: nbsphinx; extra == 'dev'
Requires-Dist: pre-commit; extra == 'dev'
Requires-Dist: pydata-sphinx-theme; extra == 'dev'
Requires-Dist: pylint; extra == 'dev'
Requires-Dist: pytest; extra == 'dev'
Requires-Dist: pytest-cov; extra == 'dev'
Requires-Dist: pytest-order; extra == 'dev'
Requires-Dist: pytest-pylint; extra == 'dev'
Requires-Dist: recommonmark; extra == 'dev'
Requires-Dist: ruff; extra == 'dev'
Requires-Dist: sphinx-autoapi; extra == 'dev'
Requires-Dist: sphinx-autobuild; extra == 'dev'
Requires-Dist: sphinx-click; extra == 'dev'
Requires-Dist: sphinx-rtd-theme; extra == 'dev'
Requires-Dist: sphinx>=1.6; extra == 'dev'
Requires-Dist: sphinxcontrib-napoleon; extra == 'dev'
Requires-Dist: twine; extra == 'dev'
Provides-Extra: docs
Requires-Dist: autodoc; extra == 'docs'
Requires-Dist: autodocsumm; extra == 'docs'
Requires-Dist: furo; extra == 'docs'
Requires-Dist: lxml[html-clean]; extra == 'docs'
Requires-Dist: m2r; extra == 'docs'
Requires-Dist: myst-parser; extra == 'docs'
Requires-Dist: nbsphinx; extra == 'docs'
Requires-Dist: pydata-sphinx-theme; extra == 'docs'
Requires-Dist: recommonmark; extra == 'docs'
Requires-Dist: sphinx-autoapi; extra == 'docs'
Requires-Dist: sphinx-autobuild; extra == 'docs'
Requires-Dist: sphinx-click; extra == 'docs'
Requires-Dist: sphinx-rtd-theme; extra == 'docs'
Requires-Dist: sphinx>=1.6; extra == 'docs'
Requires-Dist: sphinxcontrib-napoleon; extra == 'docs'
Provides-Extra: test
Requires-Dist: codecov; extra == 'test'
Requires-Dist: coverage[toml]; extra == 'test'
Requires-Dist: isort; extra == 'test'
Requires-Dist: pylint; extra == 'test'
Requires-Dist: pytest; extra == 'test'
Requires-Dist: pytest-cov; extra == 'test'
Requires-Dist: pytest-order; extra == 'test'
Requires-Dist: pytest-pylint; extra == 'test'
Requires-Dist: ruff; extra == 'test'
